dsgen/__dsq_main__.py
dsgen/__init__.py
dsgen/base.py
dsgen/message.py
dsgen/runtime.py
dsgen/store.py
dsgen/utils.py
dsgen/contrib/__init__.py
dsgen/contrib/amqp.py
dsgen/contrib/base.py
dsgen/contrib/celery.py
dsgen/contrib/redis.py
dsgen/db/__init__.py
dsgen/db/router/__init__.py
dsgen/db/router/base.py
dsgen/db/router/factory.py
dsgen/db/router/prototype.py
dsgen/file/__init__.py
dsgen/file/exception.py
dsgen/file/reader.py
dsgen/format/__init__.py
dsgen/format/json.py
dsgen/format/toml.py
dsgen/format/xml.py
dsgen/format/yaml.py
dsgen/middleware/__init__.py
dsgen/middleware/common.py
dsgen/schema/__init__.py
dsgen/schema/base.py
dsgen/schema/parser.py
dsgen/task/__init__.py
dsgen/task/dispatch.py
dsgen/task/schedule.py
dsgen-2.23012005.1342.dist-info/METADATA
dsgen-2.23012005.1342.dist-info/WHEEL
dsgen-2.23012005.1342.dist-info/entry_points.txt
dsgen-2.23012005.1342.dist-info/top_level.txt
dsgen-2.23012005.1342.dist-info/RECORD
