Metadata-Version: 2.1
Name: dsgen
Version: 2.23012005.1342
Summary: Generator For Django Settings
Author-email: Cecelia Chen <cecelia@studio.home>
License: Apache License
Project-URL: Homepage, http://rcs.studio.home/project/dsgen
Keywords: Django,configuration
Classifier: Development Status :: 5 - Production/Stable
Classifier: Intended Audience :: Developers
Classifier: License :: OSI Approved :: Apache Software License
Classifier: Operating System :: OS Independent
Classifier: Programming Language :: Python
Classifier: Programming Language :: Python :: 3
Classifier: Programming Language :: Python :: 3 :: Only
Classifier: Topic :: Software Development :: Libraries :: Python Modules
Requires-Python: >=3.8
Requires-Dist: Django >4.2
Requires-Dist: dmprj >0.2.11
Provides-Extra: celery
Requires-Dist: celery ; extra == 'celery'
Requires-Dist: kombu ; extra == 'celery'
Provides-Extra: redis
Requires-Dist: redis ; extra == 'redis'
Provides-Extra: toml
Requires-Dist: toml ; extra == 'toml'
Requires-Dist: tomli ; extra == 'toml'
Provides-Extra: yaml
Requires-Dist: pyyaml ; extra == 'yaml'
